aiotuya/__init__.py
aiotuya/__main__.py
aiotuya/aiotuya.py
aiotuya/provision.py
aiotuya-0.1.0b2.dist-info/LICENSE
aiotuya-0.1.0b2.dist-info/METADATA
aiotuya-0.1.0b2.dist-info/WHEEL
aiotuya-0.1.0b2.dist-info/entry_points.txt
aiotuya-0.1.0b2.dist-info/top_level.txt
aiotuya-0.1.0b2.dist-info/RECORD
