Metadata-Version: 2.1
Name: aiotuya
Version: 0.1.0b2
Summary: Pure Python library to control/provision Tuya devices
Home-page: https://github.com/frawau/aiotuya
Author: François Wautier, Max Isom et al.
Author-email: francois@wautier.eu
License: MIT
Keywords: Tuya,IoT,WiFi,Home Automation,asyncio
Platform: unix
Platform: linux
Platform: osx
Classifier: Development Status :: 4 - Beta
Classifier: Intended Audience :: Developers
Classifier: Intended Audience :: System Administrators
Classifier: License :: OSI Approved :: MIT License
Classifier: Operating System :: POSIX
Classifier: Operating System :: POSIX :: Linux
Classifier: Operating System :: MacOS :: MacOS X
Classifier: Topic :: Software Development :: Libraries
Classifier: Programming Language :: Python
Classifier: Programming Language :: Python :: 3.5
Classifier: Programming Language :: Python :: 3.6
Classifier: Programming Language :: Python :: Implementation :: CPython
